django_fingerprinting/__init__.py
django_fingerprinting/templatetags/__init__.py
django_fingerprinting/templatetags/fingerprinting.py
django_fingerprinting-1.0.3.dist-info/DESCRIPTION.rst
django_fingerprinting-1.0.3.dist-info/METADATA
django_fingerprinting-1.0.3.dist-info/RECORD
django_fingerprinting-1.0.3.dist-info/WHEEL
django_fingerprinting-1.0.3.dist-info/metadata.json
django_fingerprinting-1.0.3.dist-info/top_level.txt
